[
  {
    "model_id": "odats/rl_nmt_2026_04_08_10_56",
    "author": "unknown",
    "title": "odats/rl_nmt_2026_04_08_10_56",
    "downloads": 0,
    "likes": 0,
    "tags": [
      "transformers",
      "safetensors",
      "gemma3_text",
      "text-generation",
      "generated_from_trainer",
      "trl",
      "grpo",
      "conversational",
      "arxiv:2402.03300",
      "base_model:google/gemma-3-1b-it",
      "base_model:finetune:google/gemma-3-1b-it",
      "text-generation-inference",
      "endpoints_compatible",
      "region:us"
    ],
    "pipeline_tag": "text-generation",
    "library": "transformers",
    "created_at": "2026-04-08T10:56:09.000Z",
    "last_modified": "2026-04-08T13:58:04.000Z",
    "days_since_creation": 0,
    "url": "https://huggingface.co/odats/rl_nmt_2026_04_08_10_56",
    "date": "2026-04-08",
    "source": "huggingface_model",
    "type": "model",
    "research_score": 0.4
  },
  {
    "model_id": "odats/rl_nmt_2026_04_08_10_02",
    "author": "unknown",
    "title": "odats/rl_nmt_2026_04_08_10_02",
    "downloads": 0,
    "likes": 0,
    "tags": [
      "transformers",
      "safetensors",
      "gemma3_text",
      "text-generation",
      "generated_from_trainer",
      "grpo",
      "trl",
      "conversational",
      "arxiv:2402.03300",
      "base_model:google/gemma-3-1b-it",
      "base_model:finetune:google/gemma-3-1b-it",
      "text-generation-inference",
      "endpoints_compatible",
      "region:us"
    ],
    "pipeline_tag": "text-generation",
    "library": "transformers",
    "created_at": "2026-04-08T10:02:50.000Z",
    "last_modified": "2026-04-08T13:54:02.000Z",
    "days_since_creation": 0,
    "url": "https://huggingface.co/odats/rl_nmt_2026_04_08_10_02",
    "date": "2026-04-08",
    "source": "huggingface_model",
    "type": "model",
    "research_score": 0.4
  },
  {
    "model_id": "odats/rl_nmt_2026_04_08_10_28",
    "author": "unknown",
    "title": "odats/rl_nmt_2026_04_08_10_28",
    "downloads": 0,
    "likes": 0,
    "tags": [
      "transformers",
      "safetensors",
      "gemma3_text",
      "text-generation",
      "generated_from_trainer",
      "trl",
      "grpo",
      "conversational",
      "arxiv:2402.03300",
      "base_model:google/gemma-3-1b-it",
      "base_model:finetune:google/gemma-3-1b-it",
      "text-generation-inference",
      "endpoints_compatible",
      "region:us"
    ],
    "pipeline_tag": "text-generation",
    "library": "transformers",
    "created_at": "2026-04-08T10:28:39.000Z",
    "last_modified": "2026-04-08T13:52:00.000Z",
    "days_since_creation": 0,
    "url": "https://huggingface.co/odats/rl_nmt_2026_04_08_10_28",
    "date": "2026-04-08",
    "source": "huggingface_model",
    "type": "model",
    "research_score": 0.4
  },
  {
    "model_id": "odats/rl_nmt_2026_04_08_09_32",
    "author": "unknown",
    "title": "odats/rl_nmt_2026_04_08_09_32",
    "downloads": 0,
    "likes": 0,
    "tags": [
      "transformers",
      "safetensors",
      "gemma3_text",
      "text-generation",
      "generated_from_trainer",
      "grpo",
      "trl",
      "conversational",
      "arxiv:2402.03300",
      "base_model:google/gemma-3-1b-it",
      "base_model:finetune:google/gemma-3-1b-it",
      "text-generation-inference",
      "endpoints_compatible",
      "region:us"
    ],
    "pipeline_tag": "text-generation",
    "library": "transformers",
    "created_at": "2026-04-08T09:32:32.000Z",
    "last_modified": "2026-04-08T13:49:51.000Z",
    "days_since_creation": 0,
    "url": "https://huggingface.co/odats/rl_nmt_2026_04_08_09_32",
    "date": "2026-04-08",
    "source": "huggingface_model",
    "type": "model",
    "research_score": 0.4
  }
]